setup.py
bin/sortest
sortest/__init__.py
sortest.egg-info/PKG-INFO
sortest.egg-info/SOURCES.txt
sortest.egg-info/dependency_links.txt
sortest.egg-info/not-zip-safe
sortest.egg-info/requires.txt
sortest.egg-info/top_level.txt
test/test.py