Metadata-Version: 1.0
Name: sortest
Version: 0.0.10
Summary: Continuous testing in Python with sorting by test speed and auto-restart when files change
Home-page: https://github.com/eigenhombre/sortest
Author: John Jacobsen
Author-email: john@mail.npxdesigns.com
License: EPL
Platform: UNKNOWN
